{"otherData": {},"traceEvents":[{"cat":"function","dur":150426,"name":"void __cdecl Albedo::WindowsWindow::Init(const struct Albedo::WindowProps &)","ph":"X","pid":0,"tid":3109660102,"ts":417277221790},{"cat":"function","dur":388721,"name":"__cdecl Albedo::WindowsWindow::WindowsWindow(const struct Albedo::WindowProps &)","ph":"X","pid":0,"tid":3109660102,"ts":417277221776},{"cat":"function","dur":75,"name":"void __cdecl Albedo::OpenGLRendererAPI::Init(void)","ph":"X","pid":0,"tid":3109660102,"ts":417277611382},{"cat":"function","dur":37,"name":"__cdecl Albedo::OpenGLVertexArray::OpenGLVertexArray(void)","ph":"X","pid":0,"tid":3109660102,"ts":417277611918},{"cat":"function","dur":197,"name":"__cdecl Albedo::OpenGLVertexBuffer::OpenGLVertexBuffer(float *,unsigned int)","ph":"X","pid":0,"tid":3109660102,"ts":417277612326},{"cat":"function","dur":2,"name":"void __cdecl Albedo::OpenGLVertexBuffer::Bind(void) const","ph":"X","pid":0,"tid":3109660102,"ts":417277612776},{"cat":"function","dur":172,"name":"void __cdecl Albedo::OpenGLVertexArray::AddVertexBuffer(const class std::shared_ptr<class Albedo::VertexBuffer> &)","ph":"X","pid":0,"tid":3109660102,"ts":417277612767},{"cat":"function","dur":185,"name":"__cdecl Albedo::OpenGLIndexBuffer::OpenGLIndexBuffer(unsigned int *,unsigned int)","ph":"X","pid":0,"tid":3109660102,"ts":417277613039},{"cat":"function","dur":21,"name":"void __cdecl Albedo::OpenGLTexture2D::Bind(unsigned int) const","ph":"X","pid":0,"tid":3109660102,"ts":417277613368},{"cat":"function","dur":171,"name":"__cdecl Albedo::OpenGLTexture2D::OpenGLTexture2D(unsigned int,unsigned int)","ph":"X","pid":0,"tid":3109660102,"ts":417277613348},{"cat":"function","dur":572,"name":"void __cdecl Albedo::OpenGLTexture2D::SetData(void *,unsigned int)","ph":"X","pid":0,"tid":3109660102,"ts":417277613698},{"cat":"function","dur":2,"name":"void __cdecl Albedo::OpenGLIndexBuffer::Bind(void) const","ph":"X","pid":0,"tid":3109660102,"ts":417277614472},{"cat":"function","dur":102,"name":"void __cdecl Albedo::OpenGLVertexArray::SetIndexBuffer(const class std::shared_ptr<class Albedo::IndexBuffer> &)","ph":"X","pid":0,"tid":3109660102,"ts":417277614470},{"cat":"function","dur":449,"name":"class std::basic_string<char,struct std::char_traits<char>,class std::allocator<char> > __cdecl Albedo::OpenGLShader::readFile(const class std::basic_string<char,struct std::char_traits<char>,class std::allocator<char> > &)","ph":"X","pid":0,"tid":3109660102,"ts":417277614724},{"cat":"function","dur":107,"name":"class std::unordered_map<unsigned int,class std::basic_string<char,struct std::char_traits<char>,class std::allocator<char> >,struct std::hash<unsigned int>,struct std::equal_to<unsigned int>,class std::allocator<struct std::pair<unsigned int const ,class std::basic_string<char,struct std::char_traits<char>,class std::allocator<char> > > > > __cdecl Albedo::OpenGLShader::PreProcess(const class std::basic_string<char,struct std::char_traits<char>,class std::allocator<char> > &)","ph":"X","pid":0,"tid":3109660102,"ts":417277615289},{"cat":"function","dur":8458,"name":"void __cdecl Albedo::OpenGLShader::Compile(const class std::unordered_map<unsigned int,class std::basic_string<char,struct std::char_traits<char>,class std::allocator<char> >,struct std::hash<unsigned int>,struct std::equal_to<unsigned int>,class std::allocator<struct std::pair<unsigned int const ,class std::basic_string<char,struct std::char_traits<char>,class std::allocator<char> > > > > &)","ph":"X","pid":0,"tid":3109660102,"ts":417277615505},{"cat":"function","dur":18063,"name":"__cdecl Albedo::OpenGLShader::OpenGLShader(const class std::basic_string<char,struct std::char_traits<char>,class std::allocator<char> > &)","ph":"X","pid":0,"tid":3109660102,"ts":417277614715},{"cat":"function","dur":458,"name":"void __cdecl Albedo::OpenGLShader::Bind(void)","ph":"X","pid":0,"tid":3109660102,"ts":417277632920},{"cat":"function","dur":49,"name":"void __cdecl Albedo::OpenGLShader::SetUniformInt1(const class std::basic_string<char,struct std::char_traits<char>,class std::allocator<char> > &,int)","ph":"X","pid":0,"tid":3109660102,"ts":417277633658},{"cat":"function","dur":22100,"name":"void __cdecl Albedo::Renderer2D::Init(void)","ph":"X","pid":0,"tid":3109660102,"ts":417277611822},{"cat":"function","dur":22669,"name":"void __cdecl Albedo::Renderer::Init(void)","ph":"X","pid":0,"tid":3109660102,"ts":417277611362},{"cat":"function","dur":833,"name":"void __cdecl Albedo::ImGuiLayer::OnAttach(void)","ph":"X","pid":0,"tid":3109660102,"ts":417277634139},{"cat":"function","dur":953,"name":"void __cdecl Albedo::Application::PushOverlay(class Albedo::Layer *)","ph":"X","pid":0,"tid":3109660102,"ts":417277634133},{"cat":"function","dur":413431,"name":"__cdecl Albedo::Application::Application(void)","ph":"X","pid":0,"tid":3109660102,"ts":417277221744},{"cat":"function","dur":12,"name":"__cdecl Albedo::OrthographicCamera::OrthographicCamera(float,float,float,float)","ph":"X","pid":0,"tid":3109660102,"ts":417277635281},{"cat":"function","dur":10,"name":"void __cdecl Albedo::OpenGLTexture2D::Bind(unsigned int) const","ph":"X","pid":0,"tid":3109660102,"ts":417277635403},{"cat":"function","dur":78433,"name":"__cdecl Albedo::OpenGLTexture2D::OpenGLTexture2D(const class std::basic_string<char,struct std::char_traits<char>,class std::allocator<char> > &)","ph":"X","pid":0,"tid":3109660102,"ts":417277635401},{"cat":"function","dur":12,"name":"void __cdecl Albedo::OpenGLTexture2D::Bind(unsigned int) const","ph":"X","pid":0,"tid":3109660102,"ts":417277714065},{"cat":"function","dur":76183,"name":"__cdecl Albedo::OpenGLTexture2D::OpenGLTexture2D(const class std::basic_string<char,struct std::char_traits<char>,class std::allocator<char> > &)","ph":"X","pid":0,"tid":3109660102,"ts":417277714062},{"cat":"function","dur":155033,"name":"void __cdecl AlbedoApp2D::OnAttach(void)","ph":"X","pid":0,"tid":3109660102,"ts":417277635391},{"cat":"function","dur":155153,"name":"void __cdecl Albedo::Application::PushLayer(class Albedo::Layer *)","ph":"X","pid":0,"tid":3109660102,"ts":417277635378}]}